{
  "file_path": "/var/folders/nq/lwbr1v0j6j58jstbp6bc7_0c0000gn/T/tmpwu0fdajp/sample_policy.txt",
  "file_name": "sample_policy.txt",
  "file_type": "text",
  "document_type": "policy",
  "processed_at": "2025-08-12T16:16:42.864044",
  "file_hash": "232d6221a3e49db6e13719cd01cb1434f35d95e6fe561f9de74f696faf69883f",
  "metadata": {
    "file_size": 903,
    "created_date": "2025-08-12T16:16:20.551803",
    "modified_date": "2025-08-12T16:16:20.551803"
  },
  "content": "\n    DEPARTMENT OF JUSTICE\n    Policy No. DOJ-2024-001\n    \n    STANDARD OPERATING PROCEDURE\n    Digital Evidence Collection and Preservation\n    \n    Effective Date: February 1, 2024\n    \n    1.1 PURPOSE\n    This policy establishes procedures for the collection, preservation, and handling of digital evidence in criminal investigations.\n    \n    1.2 SCOPE\n    This policy applies to all law enforcement personnel within the Department of Justice.\n    \n    1.3 DEFINITIONS\n    (a) \"Digital Evidence\" means any information stored or transmitted in digital form.\n    (b) \"Chain of Custody\" means the chronological documentation of evidence handling.\n    \n    2.1 COLLECTION PROCEDURES\n    All digital evidence must be collected in accordance with 18 U.S.C. 2703 and relevant case law.\n    \n    2.2 PRESERVATION REQUIREMENTS\n    Digital evidence must be preserved using forensic tools and techniques.\n    ",
  "summary": "\n    DEPARTMENT OF JUSTICE\n    Policy No  DOJ-2024-001\n    \n    STANDARD OPERATING PROCEDURE\n    Digital Evidence Collection and Preservation\n    \n    Effective Date: February 1, 2024\n    \n    1",
  "key_entities": {
    "dates": [
      "February 1, 2024"
    ],
    "names": [],
    "organizations": [],
    "locations": [],
    "references": [
      "Policy No. DOJ-2024-001"
    ]
  },
  "structure": {
    "sections": [],
    "headings": [
      "DEPARTMENT OF JUSTICE",
      "STANDARD OPERATING PROCEDURE",
      "1.1 PURPOSE",
      "1.2 SCOPE",
      "1.3 DEFINITIONS",
      "2.1 COLLECTION PROCEDURES",
      "2.2 PRESERVATION REQUIREMENTS"
    ],
    "paragraphs": 1,
    "word_count": 109
  },
  "tags": [
    "policy",
    "procedure",
    "guideline"
  ],
  "chunks": [
    {
      "content": "DEPARTMENT OF JUSTICE\nPolicy No. DOJ-2024-001\nSTANDARD OPERATING PROCEDURE\nDigital Evidence Collection and Preservation\nEffective Date: February 1, 2024",
      "metadata": {
        "section_number": "",
        "section_title": "",
        "policy_numbers": [
          "DOJ-2024-001"
        ],
        "dates": []
      },
      "chunk_type": "policy_section",
      "section": null,
      "start_line": 3,
      "end_line": 8
    },
    {
      "content": "1.1 PURPOSE\nThis policy establishes procedures for the collection, preservation, and handling of digital evidence in criminal investigations.",
      "metadata": {
        "section_number": "1.1",
        "section_title": "PURPOSE",
        "policy_numbers": [],
        "dates": []
      },
      "chunk_type": "policy_section",
      "section": {
        "number": "1.1",
        "title": "PURPOSE"
      },
      "start_line": 9,
      "end_line": 11
    },
    {
      "content": "1.2 SCOPE\nThis policy applies to all law enforcement personnel within the Department of Justice.",
      "metadata": {
        "section_number": "1.2",
        "section_title": "SCOPE",
        "policy_numbers": [],
        "dates": []
      },
      "chunk_type": "policy_section",
      "section": {
        "number": "1.2",
        "title": "SCOPE"
      },
      "start_line": 12,
      "end_line": 14
    },
    {
      "content": "1.3 DEFINITIONS\n(a) \"Digital Evidence\" means any information stored or transmitted in digital form.\n(b) \"Chain of Custody\" means the chronological documentation of evidence handling.",
      "metadata": {
        "section_number": "1.3",
        "section_title": "DEFINITIONS",
        "policy_numbers": [],
        "dates": []
      },
      "chunk_type": "policy_section",
      "section": {
        "number": "1.3",
        "title": "DEFINITIONS"
      },
      "start_line": 15,
      "end_line": 18
    },
    {
      "content": "2.1 COLLECTION PROCEDURES\nAll digital evidence must be collected in accordance with 18 U.S.C. 2703 and relevant case law.",
      "metadata": {
        "section_number": "2.1",
        "section_title": "COLLECTION PROCEDURES",
        "policy_numbers": [],
        "dates": []
      },
      "chunk_type": "policy_section",
      "section": {
        "number": "2.1",
        "title": "COLLECTION PROCEDURES"
      },
      "start_line": 19,
      "end_line": 21
    },
    {
      "content": "2.2 PRESERVATION REQUIREMENTS\nDigital evidence must be preserved using forensic tools and techniques.",
      "metadata": {
        "section_number": "2.2",
        "section_title": "PRESERVATION REQUIREMENTS",
        "policy_numbers": [],
        "dates": []
      },
      "chunk_type": "policy_section",
      "section": {
        "number": "2.2",
        "title": "PRESERVATION REQUIREMENTS"
      },
      "start_line": 22,
      "end_line": 24
    }
  ],
  "chunk_count": 6
}